{
    "RepositoryName": "Kumiki",
    "RepositoryDescription": "Mainly fix and anime",
    "RepositoryAuthor": "Kumiki",
    "RepositoryIcon": "https://cdn.discordapp.com/avatars/850370781456367688/d9a15adf2f9e5a3b0b0a6ed25d92432f.webp",
    "RepositoryWebsite": null,
    "DefaultHeaderImage": null,
    "RepositoryContents": [
        {
            "Name": "おにまいLock",
            "Description": "OnimaiLock",
            "MaxIOSVersion": "17.0",
            "Author": {
                "Label": "Kumiki"
            },
            "Icon": "https://cdn.discordapp.com/attachments/957426517107949612/1090178823179489280/onimailock.jpg",
            "HeaderImage": null,
            "Category": "Lock Screen",
            "Caption": "お兄ちゃんはおしまい！",
            "Screenshot": [
                "https://cdn.discordapp.com/attachments/957426517107949612/1091205233566290010/iorghasior.gif"
            ],
            "Releases": [
                {
                    "Version": "1.0",
                    "Package": "https://cdn.discordapp.com/attachments/957426517107949612/1090177834359734282/onimailock.misaka",
                    "Description": null
                },
                {
                    "Version": "1.1",
                    "Package": "https://cdn.discordapp.com/attachments/957426517107949612/1090494747241619536/onimailock.misaka",
                    "Description": "%Optional%"
                },
                {
                    "Version": "1.2",
                    "Package": "https://cdn.discordapp.com/attachments/957426517107949612/1091061708983914567/com.Kumiki.LockOnimai.misaka",
                    "Description": "File size issue fixed"
                },
                {
                    "Version": "1.3",
                    "Package": "https://cdn.discordapp.com/attachments/957426517107949612/1091195046105198643/com.Kumiki.LockOnimai.misaka",
                    "Description": "main.caml fixed"
                },
                {
                    "Version": "1.4",
                    "Package": "https://cdn.discordapp.com/attachments/957426517107949612/1091661572025368616/com.Kumiki.LockOnimai.misaka",
                    "Description": "File name fixed"
                },
                {
                    "Version": "1.5",
                    "Package": "https://cdn.discordapp.com/attachments/957426517107949612/1092132582046576780/com.Kumiki.LockOnimai.misaka",
                    "Description": "Change path"
                }
            ],
            "PackageID": "com.Kumiki.LockOnimai"
        },
        {
            "Name": "AppleEvent Lock",
            "Description": "TrollLock",
            "MaxIOSVersion": "17.0",
            "Author": {
                "Label": "YangJiii",
                "Links": [
                    {
                        "Label": "YangJiii",
                        "Link": "https://twitter.com/duongduong0908"
                    }
                ]
            },
            "Icon": "https://cdn.discordapp.com/attachments/957426517107949612/1091071310412648568/eghah.png",
            "HeaderImage": null,
            "Category": "Lock Screen",
            "Caption": null,
            "Screenshot": [
                "https://cdn.discordapp.com/attachments/957426517107949612/1091206277578891324/Appleevent.gif"
            ],
            "Releases": [
                {
                    "Version": "1.0",
                    "Package": "https://cdn.discordapp.com/attachments/957426517107949612/1091071309921923132/com.yangjiii.LockAppleEvent.misaka",
                    "Description": null
                },
                {
                    "Version": "1.1",
                    "Package": "https://cdn.discordapp.com/attachments/957426517107949612/1092135038960808007/com.Kumiki.LockAppleEvent.misaka",
                    "Description": "Change path"
                }
            ],
            "PackageID": "com.Kumiki.LockAppleEvent"
        },
        {
            "Name": "Hello Lock",
            "Description": "TrollLock",
            "MaxIOSVersion": "17.0",
            "Author": {
                "Label": "YangJiii",
                "Links": [
                    {
                        "Label": "YangJiii",
                        "Link": "https://twitter.com/duongduong0908"
                    }
                ]
            },
            "Icon": "https://cdn.discordapp.com/attachments/957426517107949612/1092136176632209419/LockHello.jpg",
            "HeaderImage": null,
            "Category": "Lock Screen",
            "Caption": "Normal,White,Black",
            "Screenshot": null,
            "Releases": [
                {
                    "Version": "1.0",
                    "Package": "https://cdn.discordapp.com/attachments/957426517107949612/1092136993372254351/HelloLock.misaka",
                    "Description": null
                },
                {
                    "Version": "2.0",
                    "Package": "https://cdn.discordapp.com/attachments/957426517107949612/1092769440476692591/com.Kumiki.LockHello.misaka",
                    "Description": "Add another color hello"
                }
            ],
            "PackageID": "com.Kumiki.LockHello"
        },
        {
            "Name": "おにまい時計",
            "Description": "OnimaiClock",
            "MaxIOSVersion": "17.0",
            "Author": {
                "Label": "Kumiki",
                "Links": [
                    {
                        "Label": "ChromiumCandy (FIX)",
                        "Link": "https://twitter.com/ChromiumCandy"
                    }
                ]
            },
            "Icon": "https://cdn.discordapp.com/attachments/957426517107949612/1089499848165826560/clock_asahi.png",
            "HeaderImage": null,
            "Category": "Clock",
            "Caption": "あさひ、ねむ、もみじを Tweak Settingsから選択可！\nAsahi, Nemu and Momiji can be selected from Tweak Settings!",
            "Screenshot": [
                "https://cdn.discordapp.com/attachments/957426517107949612/1089499848425881621/PNG.jpg"
            ],
            "Releases": [
                {
                    "Version": "1.0",
                    "Package": "https://cdn.discordapp.com/attachments/1079074514257838130/1089068018111369366/Clock_Onimai.misaka",
                    "Description": null
                },
                {
                    "Version": "1.1",
                    "Package": "https://cdn.discordapp.com/attachments/957426517107949612/1089166995527835668/com.Kumiki.ClockOnimai.misaka",
                    "Description": "File size issue fixed"
                },
                {
                    "Version": "1.2",
                    "Package": "https://cdn.discordapp.com/attachments/957426517107949612/1089500119138832484/com.Kumiki.ClockOnimai.misaka",
                    "Description": "Responding to specification changes"
                }
            ],
            "PackageID": "com.Kumiki.ClockOnimai"
        },
        {
            "Name": "Clock",
            "Description": "Normal Clock",
            "MaxIOSVersion": "17.0",
            "Author": {
                "Label": "Kumiki",
                "Links": null
            },
            "Icon": "https://cdn.discordapp.com/attachments/957426517107949612/1089498384030765097/efjaiohefu.png",
            "HeaderImage": null,
            "Category": "Clock",
            "Caption": null,
            "Screenshot": [
                "https://cdn.discordapp.com/attachments/957426517107949612/1089501898731700344/PNG.jpg"
            ],
            "Releases": [
                {
                    "Version": "1.0",
                    "Package": "https://cdn.discordapp.com/attachments/957426517107949612/1089442152909647942/clock.misaka",
                    "Description": null
                },
                {
                    "Version": "1.1",
                    "Package": "https://cdn.discordapp.com/attachments/957426517107949612/1089499112493301760/com.Kumiki.ClockNormal.misaka",
                    "Description": "Additional clock types"
                }
            ],
            "PackageID": "com.Kumiki.ClockNormal"
        },
        {
            "Name": "HideCC",
            "Description": "Hide FocusUI and Mirroring",
            "MaxIOSVersion": "15.7.1",
            "Author": {
                "Label": "Kumiki",
                "Links": [
                    {
                        "Label": "ChromiumCandy (FIX)",
                        "Link": "https://twitter.com/ChromiumCandy"
                    }
                ]
            },
            "Icon": null,
            "HeaderImage": null,
            "Category": "Control Center",
            "Caption": "集中モードとミラーリングを削除します。",
            "Screenshot": [
                "https://cdn.discordapp.com/attachments/957426517107949612/1092137920154050650/IMG_0441.jpg",
                "https://cdn.discordapp.com/attachments/957426517107949612/1092137919952728127/IMG_0440.jpg"
            ],
            "Releases": [
                {
                    "Version": "1.0",
                    "Package": "https://cdn.discordapp.com/attachments/957426517107949612/1092137919646548118/HideCC.misaka",
                    "Description": null
                },
                {
                    "Version": "1.1",
                    "Package": "https://cdn.discordapp.com/attachments/957426517107949612/1092137919646548118/HideCC.misaka",
                    "Description": "Possible to choose which to turn off."
                }
            ],
            "PackageID": "com.Kumiki.HideCC"
        },
        {
            "Name": "NoNameBatteryWidget",
            "Description": "iOS15 & iOS16",
            "MaxIOSVersion": "17.0",
            "Author": {
                "Label": "Kumiki",
                "Links": [
                    {
                        "Label": "haxi0 (iOS16)",
                        "Link": "https://twitter.com/haxi0sm"
                    },
                    {
                        "Label": "34306 (Path)",
                        "Link": "https://twitter.com/Little_34306"
                    }
                ]
            },
            "Icon": "https://cdn.discordapp.com/attachments/957426517107949612/1091350930018009198/hguirsheriu.jpg",
            "HeaderImage": null,
            "Category": "SpringBoard",
            "Caption": "Remove text from battery widget",
            "Screenshot": [
                "https://cdn.discordapp.com/attachments/957426517107949612/1089741153877905538/IMG_0381.jpg"
            ],
            "Releases": [
                {
                    "Version": "1.0",
                    "Package": "https://haxi0sm.tk/misaka/NoNameBatteryWidget.misaka",
                    "Description": null
                },        
                {
                    "Version": "1.1",
                    "Package": "https://cdn.discordapp.com/attachments/957426517107949612/1091587883942563920/com.Kumiki.NoNameBatteryWidget.misaka",
                    "Description": "Compatible with iOS15 and iOS16"
                }
            ],
            "PackageID": "com.Kumiki.NoNameBatteryWidget"
        },
        {
            "Name": "HideSwipeUnlock",
            "Description": "Only ja",
            "MaxIOSVersion": "15.7.1",
            "Author": {
                "Label": "Kumiki",
                "Links": null
            },
            "Icon": null,
            "HeaderImage": null,
            "Category": "Lock Screen",
            "Caption": "ロック画面の「上にスワイプしてロック解除」を非表示\nパスワード入力画面の「上にスワイプしてFaceID～」を「パスコードを入力」に変更",
            "Screenshot": null,
            "Releases": [
                {
                    "Version": "1.0",
                    "Package": "https://cdn.discordapp.com/attachments/957426517107949612/1094920662835019836/HideSwipeUnlock.misaka",
                    "Description": null
                },
                {
                    "Version": "1.1",
                    "Package": "https://github.com/chimaha/misakarepo/raw/main/file/com.Kumiki.HideSwipeUnlock.misaka",
                    "Description": "「上にスワイプしてロック解除」が消せていなかったので修正"
                }
            ],
            "PackageID": "com.Kumiki.HideSwipeUnlock"
        },
        {
            "Name": "[FIX]Usagi Passcode",
            "Description": "Add Misaka_Resize, Reduce File size",
            "MaxIOSVersion": "17.0",
            "Author": {
                "Label": "YangJiii",
                "Links": [
                    {
                        "Label": "YangJiii",
                        "Link": "https://twitter.com/duongduong0908"
                    }
                ]
            },
            "Icon": "https://i.kym-cdn.com/photos/images/original/002/083/322/038.gif",
            "HeaderImage": null,
            "Category": "Passcode",
            "Caption": "Change your passcode",
            "Screenshot": [
                "https://cdn.discordapp.com/attachments/1076484358774472777/1076484359676243968/IMG_0808.png"
            ],
			"Releases": [
              {
                  "Version": "1.0",
                  "Package": "https://github.com/YangJiiii/repomdc/raw/main/Files/com.yangjiii.usagipasscode.misaka",
                  "Description": "Change your passcode"
              },
              {
                "Version": "1.1",
                "Package": "https://cdn.discordapp.com/attachments/957426517107949612/1093529746169667715/com.yangjiii.usagipasscode.misaka",
                "Description": "Add Misaka_Resize, Reduce File size"
              }
            ],
            "PackageID": "com.yangjiii.usagipasscodefix"
        },
        {
            "Name": "[Fix]Big Sur Clock Icon",
            "Description": "File size issue fixed",
            "MaxIOSVersion": "15.7.1",
            "Author": {
                "Label": "YangJiii",
                "Links": [
                    {
                        "Label": "YangJiii",
                        "Link": "https://twitter.com/duongduong0908"
                    }
                ]
            },
            "Icon": "https://github.com/YangJiiii/repomdc/raw/main/Images/RepoImages/other.png",
            "HeaderImage": "https://github.com/YangJiiii/repomdc/raw/main/Images/RepoImages/banner.gif",
            "Category": "Clock",
            "Caption": "Change your clock icon",
            "Screenshot": [
                "https://github.com/YangJiiii/repomdc/raw/main/Images/RepoImages/clockiconbigsur.jpg"
            ],
			"Releases": [
              {
                  "Version": "1.0",
                  "Package": "https://github.com/YangJiiii/repomdc/raw/main/Files/com.yangjiii.bigsurclockicon.misaka",
                  "Description": "Change your clock icon"
              },
              {
                "Version": "1.0",
                "Package": "https://cdn.discordapp.com/attachments/957426517107949612/1093906854809178162/com.yangjiii.bigsurclockicon.misaka",
                "Description": "File size issue fixed"
              }
            ],
            "PackageID": "com.yangjiii.bigsurclockiconfix"
        },
        {
            "Name": "[Fix]LS UI NaYan",
            "Description": null,
            "MaxIOSVersion": "17.0",
            "Author": {
                "Label": "YangJiii",
                "Links": [
                    {
                        "Label": "YangJiii",
                        "Link": "https://twitter.com/duongduong0908"
                    }
                ]
            },
            "Icon": "https://github.com/YangJiiii/repomdc/raw/main/Images/RepoImages/lsui.png",
            "HeaderImage": null,
            "Category": "Lock Screen",
            "Caption": null,
            "Screenshot": null,
			"Releases": [
                {
                    "Version": "1.0",
                    "Package": "https://github.com/YangJiiii/repomdc/raw/main/Files/com.yangjiii.nayanlsui.misaka",
                    "Description": "Change camera and flash icon"
                },
                {
                    "Version": "1.1",
                    "Package": "https://cdn.discordapp.com/attachments/957426517107949612/1094920663271215184/com.yangjiii.nayanlsui.misaka",
                    "Description": "Add icon when charging"
                }
            ],
            "PackageID": "com.yangjiii.nayanlsuifix"
        },
        {
            "Name": "[FIX]Torch&Camera",
            "Description": "Support @2x",
            "MaxIOSVersion": "17.0",
            "Author": {
                "Label": "Huy Nguyen",
                "Links": [
                    {
                        "Label": "Huy Nguyen",
                        "Link": "https://twitter.com/Little_34306"
                    }
                ]
            },
            "Icon": "https://raw.githubusercontent.com/34306/iPA/main/img/IMG_0515.jpeg",
            "HeaderImage": "https://raw.githubusercontent.com/34306/34306.github.io/master/img/slides/2.jpg",
            "Category": "Lock Screen",
            "Caption": "checkra1n bright your light",
            "Screenshot": [
                "https://raw.githubusercontent.com/34306/iPA/main/img/torch_and_cam.PNG"
            ],
            "Releases": [
                {
                    "Version": "1.0",
                    "Package": "https://github.com/34306/iPA/releases/download/mskrp/Torch.Cam.misaka",
                    "Description": "Torch and Camera or checkra1n and snowflake? 🤣"
                },
                {
                    "Version": "1.1",
                    "Package": "https://cdn.discordapp.com/attachments/957426517107949612/1089143088963911771/com.34306.tnc.misaka",
                    "Description": "Support @2x"
                },
                {
                    "Version": "1.2",
                    "Package": "https://cdn.discordapp.com/attachments/957426517107949612/1093816406992224266/com.hn.tnc.misaka",
                    "Description": "Add icon when charging"
                }
            ],
            "PackageID": "com.hn.tncfix"
        },
        {
            "Name": "[FIX]ElementTorch",
            "Description": "Support @2x",
            "MaxIOSVersion": "17.0",
            "Author": {
                "Label": "Huy Nguyen",
                "Links": [
                    {
                        "Label": "Huy Nguyen",
                        "Link": "https://twitter.com/Little_34306"
                    }
                ]
            },
            "Icon": "https://raw.githubusercontent.com/34306/iPA/main/img/A7569540-B7B5-4073-9D1C-6960215ED017.png",
            "HeaderImage": "https://raw.githubusercontent.com/34306/iPA/main/img/suzume.gif",
            "Category": "Lock Screen",
            "Caption": "Change Torch and Camera icon to Genshin Elements\nSupport both iOS 15 and 16",
            "Screenshot": [
                "https://raw.githubusercontent.com/34306/iPA/main/img/31C4635A-A29D-4E94-B408-2E3DC063ADA6.png"
            ],
            "Releases": [
                {
                    "Version": "1.0",
                    "Package": "https://github.com/34306/iPA/releases/download/mskrp/GenshinTorch.misaka",
                    "Description": "Little 34306 in your area!"
                },
                {
                    "Version": "1.1",
                    "Package": "https://cdn.discordapp.com/attachments/957426517107949612/1089857801398009986/com.34306.gstorch.misaka",
                    "Description": "Support @2x"
                },
                {
                    "Version": "1.2",
                    "Package": "https://cdn.discordapp.com/attachments/957426517107949612/1093813623559831552/com.hn.gstorch.misaka",
                    "Description": "Add icon when charging"
                }
            ],
            "PackageID": "com.hn.gstorchfix"
        },
        {
            "Name": "[FIX]Mihari clock (Homescreen)",
            "Description": "File size issue fixed",
            "MaxIOSVersion": "15.7.1",
            "Author": {
                "Label": "Huy Nguyen",
                "Links": [
                    {
                        "Label": "Huy Nguyen",
                        "Link": "https://twitter.com/Little_34306"
                    },
                    {
                        "Label": "しまじろん (FIX)",
                        "Link": "https://twitter.com/9rv0ifi2qk8wx9r/status/1628317914263859202?s=46&t=x7qR0YjDQ5I_EkRaZojZpQ"
                    }
                ]
            },
            "Icon": "https://raw.githubusercontent.com/34306/iPA/main/img/onimai.png",
            "HeaderImage": "https://raw.githubusercontent.com/34306/34306.github.io/master/img/slides/2.jpg",
            "Category": "Clock",
            "Caption": "Mahiro-chan does not want to become a girl, Mihari 🥺",
            "Screenshot": [
                "https://raw.githubusercontent.com/34306/iPA/main/img/IMG_0530.jpeg"
            ],
            "Releases": [
                {
                    "Version": "1.0",
                    "Package": "https://github.com/34306/iPA/releases/download/mskrp/Mihari.clock.misaka",
                    "Description": "Onimaiiii!"
                },
                {
                    "Version": "1.1",
                    "Package": "https://cdn.discordapp.com/attachments/1088417197455589446/1088763508973371503/com.34306.mhrclock.misaka",
                    "Description": "File size issue fixed"
                }
            ],
            "PackageID": "com.34306.mhrclockfix"
        },
        {
            "Name": "[FIX]LS UI",
            "Description": "File size issue fixed",
            "MaxIOSVersion": "17.0",
            "Author": {
                "Label": "Coolwcat",
                "Links": [
                    {
                        "Label": "Coolwcat",
                        "Link": "https://twitter.com/coolwcat"
                    }
                ]
            },
            "Icon": "https://github.com/huligang/coolwcat/raw/main/images/icon/lsui.png",
            "HeaderImage": "https://github.com/huligang/coolwcat/raw/main/images/header/header.png",
             "Category": "Lock Screen",
             "Caption": "iOS 15&16 Change camera and flash icon \n修改锁屏相机和手电筒按钮，适用于iOS15&16系统设备使用。",
             "Screenshot": [
                 "https://github.com/huligang/coolwcat/raw/main/images/screenshot/lsui15.png",
                 "https://github.com/huligang/coolwcat/raw/main/images/screenshot/4-5-6-9g-1.png"
             ],
             "Releases": [
               {
                  "Version": "1.0",
                  "Package": "https://github.com/huligang/coolwcat/raw/main/misaka/com.coolwcat.lsuiios15.misaka",
                  "Description": null
              },
              {
                "Version": "1.1",
                "Package": "https://cdn.discordapp.com/attachments/957426517107949612/1089192913851912222/com.coolwcat.lsui15.misaka",
                "Description": "File size issue fixed"
              },
              {
                "Version": "1.2",
                "Package": "https://cdn.discordapp.com/attachments/957426517107949612/1093810374920376380/com.coolwcat.lsui15.misaka",
                "Description": "Add icon when charging"
              }
            ],
            "PackageID": "com.coolwcat.lsui15fix"
        },
        {
            "Name": "[FIX]No Older Notifications",
            "Description": "Multilingual support",
            "MaxIOSVersion": "15.7.1",
            "Author": {
                "Label": "coolwcat",
                "Links": [
                    {
                        "Label": "coolwcat",
                        "Link": "https://twitter.com/coolwcat"
                    }
                ]
            },
            "Icon": "https://github.com/huligang/coolwcat/raw/main/images/icon/nooldernotifications1.png",
            "HeaderImage": "https://github.com/huligang/coolwcat/raw/main/images/header/header1.png",
            "Category": "Lock Screen",
            "Caption": "Hide No Older Notifications and Notification Center",
            "Screenshot": [
                "https://cdn.discordapp.com/attachments/957426517107949612/1094912819582992394/noolder.jpg"
            ],
			"Releases": [
              {
                  "Version": "1.0",
                  "Package": "https://github.com/huligang/coolwcat/raw/main/misaka/com.coolwcat.nooldernotifications.misaka",
                  "Description": null
              },
              {
                "Version": "1.1",
                "Package": "https://cdn.discordapp.com/attachments/957426517107949612/1089176666640752720/com.coolwcat.nooldernotifications.misaka",
                "Description": "Delete unnecessary parts of plist files"
              },
              {
                "Version": "1.2",
                "Package": "https://cdn.discordapp.com/attachments/957426517107949612/1094908507570049024/com.coolwcat.nooldernotificationsfix.misaka",
                "Description": "Hide Notification Center"
              }
            ],
            "PackageID": "com.coolwcat.nooldernotificationsfix"
        },
        {
            "Name": "[FIX]LS PokeButton",
            "Description": "Pokemon on LS!",
            "MaxIOSVersion": "17.0",
            "Author": {
                "Label": "Sugiuta",
                "Links": [
                    {
                        "Label": "Sugiuta",
                        "Link": null
                    }
                ]
            },
            "Icon": "https://cdn.discordapp.com/attachments/957426517107949612/1093805313905393695/OrbFlashlightOff.jpg",
            "Category": "Lock Screen",
            "Caption": null,
            "Screenshot": [
                "https://cdn.discordapp.com/attachments/957426517107949612/1093805313670529094/IMG_0517.jpg"
            ],
            "Releases": [
                {
                    "Version": "0.1",
                    "Package": "https://cdn.discordapp.com/attachments/1088463131828830258/1090303346226766004/com.sugiuta.lspokebutton.misaka",
                    "Description": "Initial release"
                },
                {
                    "Version": "0.2",
                    "Package": "https://cdn.discordapp.com/attachments/957426517107949612/1093802476551028787/com.sugiuta.lspokebutton.misaka",
                    "Description": "Add icon when charging"
                }
            ],
            "PackageID": "com.sugiuta.lspokebuttonfix"
        },
        {
            "Name": "[FIX]OneCC",
            "Description": "toggle bug fix",
            "Category": "Control Center",
            "Caption": "Wanted a Samsung and a good experience?\nGoes really well with the Tomorrow Clock Font",
            "MaxIOSVersion": "17.0",
            "Author": {
                "Label": "HackZy",
                "Links": [
                    {
                        "Label": "HackZy",
                        "Link": "https://GitHub.com/hackzy01"
                    },
                    {
                        "Label": "straight-tamago (fix)",
                        "Link": "https://twitter.com/straight_tamago"
                    }
                ]
            },
            "Icon": "https://raw.githubusercontent.com/hackzy01/misio/main/assets/com.hackzy.onecc/icon.png",
            "Screenshot": [
            "https://raw.githubusercontent.com/hackzy01/misio/main/assets/com.hackzy.onecc/Screenshot1.png",
            "https://raw.githubusercontent.com/hackzy01/misio/main/assets/com.hackzy.onecc/Screenshot2.png"
            ],
            "Releases": [
                {
                    "Version": "1.0",
                    "Package": "https://raw.githubusercontent.com/hackzy01/misio/main/tweaks/com.hackzy.onecc.misaka",
                    "Description": "Special credits to YangJii who's method is used in this tweak"
                },
                {
                    "Version": "1.1",
                    "Package": "https://cdn.discordapp.com/attachments/957426517107949612/1101554513090977822/Qn7CxsC.misaka",
                    "Description": "toggle bug fix"
                }
            ],
            "PackageID": "com.hackzy.oneccfix"
        }
    ]
}
